setup.py
src/divan/__init__.py
src/divan/admin.py
src/divan/forms.py
src/divan/models.py
src/divan/timestamps.py
src/divan/backends/__init__.py
src/divan/backends/base.py
src/divan/backends/couch.py
src/divan/backends/mongo.py
src/divan/management/__init__.py
src/divan/management/commands/__init__.py
src/divan/management/commands/divanmessages.py
src/django_divan.egg-info/PKG-INFO
src/django_divan.egg-info/SOURCES.txt
src/django_divan.egg-info/dependency_links.txt
src/django_divan.egg-info/top_level.txt