Metadata-Version: 1.0
Name: django-divan
Version: 0.2.3
Summary: User-definable schemas for Django.
Home-page: http://github.com/threadsafelabs/django_divan
Author: Jonathan Lukens
Author-email: jonathan@threadsafelabs.com
License: BSD
Platform: UNKNOWN
Classifier: Intended Audience :: Developers
Classifier: License :: OSI Approved :: BSD License
Classifier: Operating System :: OS Independent
Classifier: Programming Language :: Python
Classifier: Framework :: Django
